pycrow/__init__.py
pycrow/libcrow.cpython-37m-x86_64-linux-gnu.so
pycrow/__tunels__/igris/igris.g.py
pycrow/__tunels__/igris/compat/libc/libc.g.py
pycrow/__tunels__/igris/compat/libc/assert/assert_impl.h
pycrow/__tunels__/igris/compat/libc/include/alloca.h
pycrow/__tunels__/igris/compat/libc/include/assert.h
pycrow/__tunels__/igris/compat/libc/include/ctype.h
pycrow/__tunels__/igris/compat/libc/include/endian.h
pycrow/__tunels__/igris/compat/libc/include/errno.h
pycrow/__tunels__/igris/compat/libc/include/inttypes.h
pycrow/__tunels__/igris/compat/libc/include/limits.h
pycrow/__tunels__/igris/compat/libc/include/locale.h
pycrow/__tunels__/igris/compat/libc/include/math.h
pycrow/__tunels__/igris/compat/libc/include/setjmp.h
pycrow/__tunels__/igris/compat/libc/include/stdarg.h
pycrow/__tunels__/igris/compat/libc/include/stdbool.h
pycrow/__tunels__/igris/compat/libc/include/stddef.h
pycrow/__tunels__/igris/compat/libc/include/stdint.h
pycrow/__tunels__/igris/compat/libc/include/stdio.h
pycrow/__tunels__/igris/compat/libc/include/stdlib.h
pycrow/__tunels__/igris/compat/libc/include/string.h
pycrow/__tunels__/igris/compat/libc/include/string_bsd.h
pycrow/__tunels__/igris/compat/libc/include/strings.h
pycrow/__tunels__/igris/compat/libc/include/wchar.h
pycrow/__tunels__/igris/compat/libc/include/wctype.h
pycrow/__tunels__/igris/compat/libc/include/HIDE/__stdlib.h
pycrow/__tunels__/igris/compat/libc/include/HIDE/alloca.h
pycrow/__tunels__/igris/compat/libc/include/HIDE/ctype.h
pycrow/__tunels__/igris/compat/libc/include/HIDE/errno.h
pycrow/__tunels__/igris/compat/libc/include/HIDE/inttypes.h
pycrow/__tunels__/igris/compat/libc/include/HIDE/limits.h
pycrow/__tunels__/igris/compat/libc/include/HIDE/locale.h
pycrow/__tunels__/igris/compat/libc/include/HIDE/math.h
pycrow/__tunels__/igris/compat/libc/include/HIDE/printf_impl.h
pycrow/__tunels__/igris/compat/libc/include/HIDE/setjmp.h
pycrow/__tunels__/igris/compat/libc/include/HIDE/stdarg.h
pycrow-0.1.5.dist-info/METADATA
pycrow-0.1.5.dist-info/WHEEL
pycrow-0.1.5.dist-info/top_level.txt
pycrow-0.1.5.dist-info/RECORD
