Metadata-Version: 1.0
Name: pycrow
Version: 0.1.5
Summary: Messaging system
Home-page: https://mirmik.github.io/crow/
Author: Sorokin Nikolay
Author-email: mirmikns@yandex.ru
License: MIT
Keywords: testing,cad
Platform: UNKNOWN
